LICENSE
README.md
setup.py
algo_fun/__init__.py
algo_fun/fibonacci_up_to.py
algo_fun_fibonacci.egg-info/PKG-INFO
algo_fun_fibonacci.egg-info/SOURCES.txt
algo_fun_fibonacci.egg-info/dependency_links.txt
algo_fun_fibonacci.egg-info/top_level.txt
tests/__init__.py
tests/test_fibonacci_up_to.py