Metadata-Version: 2.1
Name: algo-fun-fibonacci
Version: 0.1.0
Summary: Give the fibonacci sequence up and including a given number
Home-page: https://gitlab.com/ChristopheLagaillarde/algo_fun_fibonacci
Author: Christophe Lagaillarde
Author-email: chrislag94@gmail.com
License: MIT
License-File: LICENSE
